import_sorter/__init__.py
import_sorter/__main__.py
import_sorter/args.py
import_sorter/external.py
import_sorter/sorting.py
import_sorter/states.py
import_sorter-1.1.1.dist-info/METADATA
import_sorter-1.1.1.dist-info/WHEEL
import_sorter-1.1.1.dist-info/entry_points.txt
import_sorter-1.1.1.dist-info/top_level.txt
import_sorter-1.1.1.dist-info/RECORD
