Metadata-Version: 2.4
Name: import-sorter
Version: 1.1.1
Summary: A CLI for sorting imports at the top of a file
Author-email: AntiMach <themachinumps@gmail.com>
License-Expression: MIT AND (Apache-2.0 OR BSD-2-Clause)
Project-URL: Homepage, https://github.com/AntiMach/python-import-sorter
Classifier: Programming Language :: Python :: 3
Classifier: Operating System :: OS Independent
Requires-Python: >=3.11
Requires-Dist: pathspec>=0.12.1
